odoo8_addon_account_invoice_transmit_method-8.0.1.0.0-py2.7-nspkg.pth
odoo8_addon_account_invoice_transmit_method-8.0.1.0.0.dist-info/DESCRIPTION.rst
odoo8_addon_account_invoice_transmit_method-8.0.1.0.0.dist-info/METADATA
odoo8_addon_account_invoice_transmit_method-8.0.1.0.0.dist-info/RECORD
odoo8_addon_account_invoice_transmit_method-8.0.1.0.0.dist-info/WHEEL
odoo8_addon_account_invoice_transmit_method-8.0.1.0.0.dist-info/metadata.json
odoo8_addon_account_invoice_transmit_method-8.0.1.0.0.dist-info/namespace_packages.txt
odoo8_addon_account_invoice_transmit_method-8.0.1.0.0.dist-info/top_level.txt
odoo_addons/account_invoice_transmit_method/README.rst
odoo_addons/account_invoice_transmit_method/__init__.py
odoo_addons/account_invoice_transmit_method/__openerp__.py
odoo_addons/account_invoice_transmit_method/data/transmit_method.xml
odoo_addons/account_invoice_transmit_method/demo/partner.xml
odoo_addons/account_invoice_transmit_method/models/__init__.py
odoo_addons/account_invoice_transmit_method/models/account_invoice.py
odoo_addons/account_invoice_transmit_method/models/partner.py
odoo_addons/account_invoice_transmit_method/models/transmit_method.py
odoo_addons/account_invoice_transmit_method/security/ir.model.access.csv
odoo_addons/account_invoice_transmit_method/tests/__init__.py
odoo_addons/account_invoice_transmit_method/tests/test_invoice_transmit_method.py
odoo_addons/account_invoice_transmit_method/views/account_invoice.xml
odoo_addons/account_invoice_transmit_method/views/partner.xml
odoo_addons/account_invoice_transmit_method/views/transmit_method.xml
